sbom_git_sm/__init__.py
sbom_git_sm/__main__.py
sbom_git_sm/cli.py
sbom_git_sm/main.py
sbom_git_sm/version_config.py
sbom_git_sm-0.2.0.dist-info/licenses/LICENSE
sbom_git_sm-0.2.0.dist-info/METADATA
sbom_git_sm-0.2.0.dist-info/WHEEL
sbom_git_sm-0.2.0.dist-info/entry_points.txt
sbom_git_sm-0.2.0.dist-info/top_level.txt
sbom_git_sm-0.2.0.dist-info/RECORD
