Metadata-Version: 2.4
Name: sbom-git-sm
Version: 0.2.0
Summary: A tool to create a Software Bill of Materials (SBOM) from a git repository based on its submodules
Author-email: Janosch Meyer <janosch.code@proton.me>
License: MIT License
Keywords: sbom,git,submodules,software bill of materials,dependencies
Classifier: Development Status :: 3 - Alpha
Classifier: Intended Audience :: Developers
Classifier: Intended Audience :: System Administrators
Classifier: License :: OSI Approved :: MIT License
Classifier: Programming Language :: Python :: 3
Classifier: Programming Language :: Python :: 3.7
Classifier: Programming Language :: Python :: 3.8
Classifier: Programming Language :: Python :: 3.9
Classifier: Programming Language :: Python :: 3.10
Classifier: Programming Language :: Python :: 3.11
Classifier: Programming Language :: Python :: 3.12
Classifier: Topic :: Software Development :: Build Tools
Classifier: Topic :: Software Development :: Libraries :: Python Modules
Classifier: Topic :: System :: Software Distribution
Requires-Python: >=3.7
License-File: LICENSE
Provides-Extra: yaml
Requires-Dist: PyYAML; extra == "yaml"
Dynamic: license-file
